hertz07/__init__.py
hertz07/version.py
hertz07/prompt_injection/__init__.py
hertz07/prompt_injection/cleanser.py
hertz07/prompt_injection/detector.py
hertz07-0.1.0.dist-info/licenses/LICENSE.txt
hertz07-0.1.0.dist-info/METADATA
hertz07-0.1.0.dist-info/WHEEL
hertz07-0.1.0.dist-info/top_level.txt
hertz07-0.1.0.dist-info/RECORD
