Metadata-Version: 2.4
Name: hertz07
Version: 0.1.0
Summary: Hertz07 Python SDK for AI safety
Author-email: Hertz07 <contact@hertz07.com>
Maintainer-email: Hertz07 <contact@hertz07.com>
License: MIT
Project-URL: Homepage, https://github.com/hertz07hq/hertz07-py
Project-URL: Documentation, https://docs.hertz07.com
Project-URL: Repository, https://github.com/hertz07hq/hertz07-py
Project-URL: Bug Reports, https://github.com/hertz07hq/hertz07-py/issues
Project-URL: Changelog, https://github.com/hertz07hq/hertz07-py/blob/main/CHANGELOG.md
Keywords: ai,security,prompt-injection,llm,guardrails,safety,detection
Classifier: Development Status :: 3 - Alpha
Classifier: Intended Audience :: Developers
Classifier: License :: OSI Approved :: MIT License
Classifier: Operating System :: OS Independent
Classifier: Programming Language :: Python :: 3
Classifier: Programming Language :: Python :: 3.8
Classifier: Programming Language :: Python :: 3.9
Classifier: Programming Language :: Python :: 3.10
Classifier: Programming Language :: Python :: 3.11
Classifier: Programming Language :: Python :: 3.12
Classifier: Topic :: Security
Classifier: Topic :: Scientific/Engineering :: Artificial Intelligence
Classifier: Topic :: Software Development :: Libraries :: Python Modules
Requires-Python: >=3.8
License-File: LICENSE.txt
Requires-Dist: pydantic>=2.0.0
Requires-Dist: groq>=0.4.0
Requires-Dist: python-dotenv>=1.0.0
Provides-Extra: dev
Requires-Dist: pytest>=7.0.0; extra == "dev"
Requires-Dist: pytest-asyncio>=0.21.0; extra == "dev"
Requires-Dist: black>=23.0.0; extra == "dev"
Requires-Dist: isort>=5.12.0; extra == "dev"
Requires-Dist: flake8>=6.0.0; extra == "dev"
Requires-Dist: mypy>=1.0.0; extra == "dev"
Requires-Dist: pre-commit>=3.0.0; extra == "dev"
Provides-Extra: docs
Requires-Dist: sphinx>=7.0.0; extra == "docs"
Requires-Dist: sphinx-rtd-theme>=1.3.0; extra == "docs"
Requires-Dist: myst-parser>=2.0.0; extra == "docs"
Provides-Extra: test
Requires-Dist: pytest>=7.0.0; extra == "test"
Requires-Dist: pytest-asyncio>=0.21.0; extra == "test"
Requires-Dist: pytest-cov>=4.0.0; extra == "test"
Requires-Dist: httpx>=0.24.0; extra == "test"
Dynamic: license-file
